{
  "props": {
    "providers": {
      "type": {
        "name": "arrayOf",
        "description": "Array&lt;{ id: 'apple'<br>&#124;&nbsp;'auth0'<br>&#124;&nbsp;'cognito'<br>&#124;&nbsp;'credentials'<br>&#124;&nbsp;'discord'<br>&#124;&nbsp;'facebook'<br>&#124;&nbsp;'fusionauth'<br>&#124;&nbsp;'github'<br>&#124;&nbsp;'gitlab'<br>&#124;&nbsp;'google'<br>&#124;&nbsp;'instagram'<br>&#124;&nbsp;'keycloak'<br>&#124;&nbsp;'line'<br>&#124;&nbsp;'linkedin'<br>&#124;&nbsp;'microsoft-entra-id'<br>&#124;&nbsp;'nodemailer'<br>&#124;&nbsp;'okta'<br>&#124;&nbsp;'passkey'<br>&#124;&nbsp;'slack'<br>&#124;&nbsp;'spotify'<br>&#124;&nbsp;'tiktok'<br>&#124;&nbsp;'twitch'<br>&#124;&nbsp;'twitter', name: string }&gt;"
      },
      "default": "[]"
    },
    "signIn": {
      "type": { "name": "func" },
      "default": "undefined",
      "signature": {
        "type": "function(provider: AuthProvider, formData: FormData, callbackUrl: string) => void | Promise<AuthResponse>",
        "describedArgs": ["provider", "formData", "callbackUrl"]
      }
    },
    "slotProps": {
      "type": {
        "name": "shape",
        "description": "{ emailField?: object, forgotPasswordLink?: object, passwordField?: object, signUpLink?: object, submitButton?: object }"
      },
      "default": "{}"
    },
    "slots": {
      "type": {
        "name": "shape",
        "description": "{ emailField?: elementType, forgotPasswordLink?: elementType, passwordField?: elementType, signUpLink?: elementType, submitButton?: elementType, subtitle?: elementType, title?: elementType }"
      },
      "default": "{}",
      "additionalInfo": { "slotsApi": true }
    },
    "sx": {
      "type": {
        "name": "union",
        "description": "Array&lt;func<br>&#124;&nbsp;object<br>&#124;&nbsp;bool&gt;<br>&#124;&nbsp;func<br>&#124;&nbsp;object"
      },
      "additionalInfo": { "sx": true }
    }
  },
  "name": "SignInPage",
  "imports": [
    "import { SignInPage } from '@toolpad/core/SignInPage';",
    "import { SignInPage } from '@toolpad/core';"
  ],
  "slots": [
    {
      "name": "emailField",
      "description": "The custom email field component used in the credentials form.",
      "default": "TextField",
      "class": null
    },
    {
      "name": "passwordField",
      "description": "The custom password field component used in the credentials form.",
      "default": "TextField",
      "class": null
    },
    {
      "name": "submitButton",
      "description": "The custom submit button component used in the credentials form.",
      "default": "LoadingButton",
      "class": null
    },
    {
      "name": "forgotPasswordLink",
      "description": "The custom forgot password link component used in the credentials form.",
      "default": "Link",
      "class": null
    },
    {
      "name": "signUpLink",
      "description": "The custom sign up link component used in the credentials form.",
      "default": "Link",
      "class": null
    },
    {
      "name": "title",
      "description": "A component to override the default title section",
      "default": "Typography",
      "class": null
    },
    {
      "name": "subtitle",
      "description": "A component to override the default subtitle section",
      "default": "Typography",
      "class": null
    }
  ],
  "classes": [],
  "spread": true,
  "themeDefaultProps": false,
  "muiName": "SignInPage",
  "filename": "/packages/toolpad-core/src/SignInPage/SignInPage.tsx",
  "inheritance": null,
  "demos": "<ul><li><a href=\"/toolpad/core/react-sign-in-page/\">Sign-in Page</a></li></ul>",
  "cssComponent": false
}
